munin/__init__.py
munin/munin.py
munin/py.typed
munin_observers-0.2.1.dist-info/LICENSE.txt
munin_observers-0.2.1.dist-info/METADATA
munin_observers-0.2.1.dist-info/WHEEL
munin_observers-0.2.1.dist-info/top_level.txt
munin_observers-0.2.1.dist-info/RECORD
