Metadata-Version: 2.1
Name: munin-observers
Version: 0.2.1
Summary: Your one-stop-shop for observer synchronization.
Home-page: https://github.com/hedesandxlii/munin-observers
Author: André Hedesand
Author-email: andre.hedesand@gmail.com
License: BSD 3-Clause License
Keywords: munin,observer,listener,signal,pattern,synchronization
Platform: UNKNOWN
Classifier: License :: OSI Approved :: BSD License
Classifier: Programming Language :: Python :: 3
Classifier: Programming Language :: Python :: 3.8
Classifier: Programming Language :: Python :: 3 :: Only
Classifier: Typing :: Typed
Classifier: Intended Audience :: Developers
Classifier: Topic :: Software Development :: Libraries
Classifier: Operating System :: OS Independent
License-File: LICENSE.txt
Provides-Extra: dev
Requires-Dist: coverage[toml] ; extra == 'dev'
Requires-Dist: mypy ; extra == 'dev'
Requires-Dist: black ; extra == 'dev'
Requires-Dist: pytest ; extra == 'dev'
Requires-Dist: pytest-cov ; extra == 'dev'
Requires-Dist: pytest-mypy ; extra == 'dev'
Requires-Dist: twine ; extra == 'dev'
Provides-Extra: examples
Requires-Dist: PySide6 ; extra == 'examples'
